Metadata-Version: 1.1
Name: django-url-tracker
Version: 0.1.3
Summary: A little app that trackes URL changes in a database table to provide HTTP 301 & 410 on request.
Home-page: https://github.com/tangentlabs/django-url-tracker
Author: Sebastian Vetter
Author-email: sebastian.vetter@tangentone.com.au
License: BSD
Keywords: seo,django,framework
Platform: UNKNOWN
Classifier: Development Status :: 3 - Alpha
Classifier: Environment :: Web Environment
Classifier: Framework :: Django
Classifier: Intended Audience :: Developers
Classifier: Programming Language :: Python
Classifier: License :: OSI Approved :: Apache Software License
Classifier: License :: OSI Approved :: BSD License
Classifier: Operating System :: OS Independent
Classifier: Topic :: Software Development
